bleico/__init__.py
bleico/ble_device.py
bleico/ble_scanner_widget.py
bleico/characteristic_metadata_widget.py
bleico/console_log.py
bleico/devtools.py
bleico/set_tooltip_dialog.py
bleico/set_value_dialog.py
bleico/socket_client_server.py
bleico/systrayicon.py
bleico/icons/BARCODE_SCANNER.png
bleico/icons/BLOOD_PRESSURE_ARM.png
bleico/icons/BLOOD_PRESSURE_WRIST.png
bleico/icons/CARD_READER.png
bleico/icons/CYCLING_CADENCE_SENSOR.png
bleico/icons/CYCLING_CYCLING_COMPUTER.png
bleico/icons/CYCLING_POWER_SENSOR.png
bleico/icons/CYCLING_SPEED_AND_CADENCE_SENSOR.png
bleico/icons/CYCLING_SPEED_SENSOR.png
bleico/icons/DIGITAL_PEN.png
bleico/icons/DIGITIZER_TABLET.png
bleico/icons/FINGERTIP.png
bleico/icons/GAMEPAD.png
bleico/icons/GENERIC_BARCODE_SCANNER.png
bleico/icons/GENERIC_BLOOD_PRESSURE.png
bleico/icons/GENERIC_CLOCK.png
bleico/icons/GENERIC_COMPUTER.png
bleico/icons/GENERIC_CONTINUOUS_GLUCOSE_MONITOR.png
bleico/icons/GENERIC_CYCLING.png
bleico/icons/GENERIC_DISPLAY.png
bleico/icons/GENERIC_ENVIRONMENTAL_SENSOR.png
bleico/icons/GENERIC_EYE-GLASSES.png
bleico/icons/GENERIC_GLUCOSE_METER.png
bleico/icons/GENERIC_HEART_RATE_SENSOR.png
bleico/icons/GENERIC_INSULIN_PUMP.png
bleico/icons/GENERIC_KEYRING.png
bleico/icons/GENERIC_MEDIA_PLAYER.png
bleico/icons/GENERIC_MEDICATION_DELIVERY.png
bleico/icons/GENERIC_OUTDOOR_SPORTS_ACTIVITY.png
bleico/icons/GENERIC_PERSONAL_MOBILITY_DEVICE.png
bleico/icons/GENERIC_PHONE.png
bleico/icons/GENERIC_PULSE_OXIMETER.png
bleico/icons/GENERIC_REMOTE_CONTROL.png
bleico/icons/GENERIC_RUNNING_WALKING_SENSOR.png
bleico/icons/GENERIC_TAG.png
bleico/icons/GENERIC_THERMOMETER.png
bleico/icons/GENERIC_WATCH.png
bleico/icons/GENERIC_WEIGHT_SCALE.png
bleico/icons/HEART_RATE_SENSOR_HEART_RATE_BELT.png
bleico/icons/HUMAN_INTERFACE_DEVICE_(HID).png
bleico/icons/INSULIN_PEN.png
"bleico/icons/INSULIN_PUMP,_DURABLE_PUMP.png"
"bleico/icons/INSULIN_PUMP,_PATCH_PUMP.png"
bleico/icons/JOYSTICK.png
bleico/icons/KEYBOARD.png
bleico-0.0.2.dist-info/AUTHORS
bleico-0.0.2.dist-info/LICENSE
bleico-0.0.2.dist-info/METADATA
bleico-0.0.2.dist-info/WHEEL
bleico-0.0.2.dist-info/top_level.txt
bleico-0.0.2.dist-info/RECORD
