Metadata-Version: 2.1
Name: bleico
Version: 0.0.2
Summary: Bluetooth Low Energy System Tray App
Home-page: http://github.com/Carglglz/bleico
Author: Carlos Gil Gonzalez
Author-email: carlosgilglez@gmail.com
License: GPL-3.0
Platform: UNKNOWN
Classifier: Intended Audience :: Developers
Classifier: Intended Audience :: Science/Research
Classifier: Intended Audience :: Education
Classifier: License :: OSI Approved :: GNU General Public License v3 (GPLv3)
Classifier: Programming Language :: Python :: 3.7
Classifier: Programming Language :: Python :: 3.8
Classifier: Topic :: System :: Monitoring
Classifier: Topic :: Scientific/Engineering
Classifier: Topic :: Software Development :: Embedded Systems
Requires-Dist: bleak (>=0.8.0)
Requires-Dist: PyQt5
Requires-Dist: bleak-sigspec (>=0.0.4)
